g_ttt
