Metadata-Version: 1.0
Name: g-ttt
Version: 0.3
Summary: A cool tic tac toe game
Home-page: UNKNOWN
Author: Gustavo Oliveira
Author-email: gugmt15@gmail.com
License: UNKNOWN
Platform: UNKNOWN
